configuration/__init__.py
configuration/config.py
python_config_service/__init__.py
python_config_service-0.2.2.dist-info/METADATA
python_config_service-0.2.2.dist-info/WHEEL
python_config_service-0.2.2.dist-info/top_level.txt
python_config_service-0.2.2.dist-info/RECORD
